roghib/__init__.py
roghib-1.0.0.dist-info/LICENSE
roghib-1.0.0.dist-info/METADATA
roghib-1.0.0.dist-info/WHEEL
roghib-1.0.0.dist-info/top_level.txt
roghib-1.0.0.dist-info/RECORD
