Metadata-Version: 2.1
Name: roghib
Version: 1.0.0
Summary: Build anything with Roghib
Home-page: https://github.com/osscript/roghib
Author: Roghib
Author-email: master@roghib.com
License: UNKNOWN
Project-URL: Bug Tracker, https://github.com/osscript/roghib/issues
Platform: UNKNOWN
Classifier: Programming Language :: Python :: 3
Classifier: License :: OSI Approved :: MIT License
Classifier: Operating System :: OS Independent
Requires-Python: >=3.9
